netwix/__init__.py
netwix/exceptions.py
netwix/types.py
tests/__init__.py
tests/netwixTest.py
netwix-0.1.8.dist-info/LICENSE
netwix-0.1.8.dist-info/METADATA
netwix-0.1.8.dist-info/WHEEL
netwix-0.1.8.dist-info/top_level.txt
netwix-0.1.8.dist-info/RECORD
