Metadata-Version: 2.1
Name: netwix
Version: 0.1.8
Summary: Netwix is a python client for Netflix. With netwix by simply entering the Netflix ID the user can access data related to movies and tv shows available on Netflix
Home-page: https://www.github.com/new92/netwix
Author: new92
Author-email: new92github@gmail.com
Maintainer: new92
Maintainer-email: new92github@gmail.com
License: MIT
Project-URL: Github Repository, https://github.com/new92/netwix
Keywords: python netflix movies series data retrieval module
Classifier: License :: OSI Approved :: MIT License
Classifier: Programming Language :: Python :: 3
Classifier: Programming Language :: Python :: 3.6
Classifier: Programming Language :: Python :: 3.7
Classifier: Programming Language :: Python :: 3.8
Classifier: Programming Language :: Python :: 3.9
Classifier: Programming Language :: Python :: 3.10
Classifier: Programming Language :: Python :: 3.11
Requires-Python: >=3.6
License-File: LICENSE
Requires-Dist: requests
Requires-Dist: bs4
